README.md
setup.py
cloudflared/__init__.py
cloudflared/cloudflare.py
cloudflared/utils.py
cloudflared.egg-info/PKG-INFO
cloudflared.egg-info/SOURCES.txt
cloudflared.egg-info/dependency_links.txt
cloudflared.egg-info/requires.txt
cloudflared.egg-info/top_level.txt